{
    "1": {
        "title": "E-car financial support 2021"
    },
    "2": {
        "title": "Diesel to become 20 cents more expensive"
    },
    "3": {
        "title": "Much cleaner than expected"
    },
    "4": {
        "title": "30,000 euros as a gift for a Tesla"
    },
    "5": {
        "title": "Redistribution from poor to green"
    },
    "6": {
        "title": "Tough blow for manufacturers Plug-in premium no longer available"
    },
    "7": {
        "title": "For the climate and against China"
    },
    "9": {
        "title": "Power consumption: this is how much an electric car really consumes"
    },
    "10": {
        "title": "A yellow sheet shows what customers would save with e-cars"
    },
    "12": {
        "title": "Autonomous driving success or flop?"
    },
    "16": {
        "title": "Raw materials for e-car battery"
    },
    "17": {
        "title": "Car manufacturers as software giants"
    },
    "19": {
        "title": "Even without the Berlin factory: German car industry already earns money from Tesla"
    },
    "23": {
        "title": "Here come the wonder batteries"
    },
    "24": {
        "title": "Electricity, routes, distribution grids"
    },
    "26": {
        "title": "Car blogger takes Tesla model apart"
    }
}